{
  "updated_at": "2026-07-16 12:13",
  "indicators": [
    {
      "code": "002963",
      "name": "易方达黄金ETF联接C",
      "rsi14": 35.04,
      "ma5": 2.82502,
      "ma20": 2.85194,
      "prev_ma5": 2.83968,
      "prev_ma20": 2.86195,
      "macd_dif": -0.05510372,
      "macd_dea": -0.06176201,
      "macd_hist": 0.01331659,
      "macd_trend": "bullish",
      "latest_price": 2.794,
      "prices_used": 60
    },
    {
      "code": "000307",
      "name": "易方达黄金ETF联接A",
      "rsi14": 35.11,
      "ma5": 2.91458,
      "ma20": 2.942075,
      "prev_ma5": 2.92966,
      "prev_ma20": 2.95236,
      "macd_dif": -0.05654524,
      "macd_dea": -0.06341069,
      "macd_hist": 0.0137309,
      "macd_trend": "bullish",
      "latest_price": 2.8827,
      "prices_used": 60
    },
    {
      "code": "010990",
      "name": "南方有色金属ETF联接E",
      "rsi14": 37.61,
      "ma5": 1.69336,
      "ma20": 1.80429,
      "prev_ma5": 1.69802,
      "prev_ma20": 1.819245,
      "macd_dif": -0.06507609,
      "macd_dea": -0.05671209,
      "macd_hist": -0.01672801,
      "macd_trend": "bearish",
      "latest_price": 1.6814,
      "prices_used": 60
    },
    {
      "code": "011840",
      "name": "天弘中证人工智能主题指数C",
      "rsi14": 49.0,
      "ma5": 2.08732,
      "ma20": 2.08435,
      "prev_ma5": 2.09056,
      "prev_ma20": 2.080925,
      "macd_dif": 0.02288941,
      "macd_dea": 0.03198499,
      "macd_hist": -0.01819116,
      "macd_trend": "bearish",
      "latest_price": 2.0294,
      "prices_used": 60
    },
    {
      "code": "012885",
      "name": "华夏中证光伏产业ETF联接A",
      "rsi14": 26.63,
      "ma5": 0.55736,
      "ma20": 0.61115,
      "prev_ma5": 0.56322,
      "prev_ma20": 0.616775,
      "macd_dif": -0.02924996,
      "macd_dea": -0.02221062,
      "macd_hist": -0.01407868,
      "macd_trend": "bearish",
      "latest_price": 0.543,
      "prices_used": 60
    },
    {
      "code": "015790",
      "name": "永赢高端装备智选混合C",
      "rsi14": 37.14,
      "ma5": 1.35314,
      "ma20": 1.401415,
      "prev_ma5": 1.37762,
      "prev_ma20": 1.40836,
      "macd_dif": -0.02894487,
      "macd_dea": -0.01257031,
      "macd_hist": -0.03274913,
      "macd_trend": "bearish",
      "latest_price": 1.2271,
      "prices_used": 60
    },
    {
      "code": "025647",
      "name": "平安高端装备混合C",
      "rsi14": 35.16,
      "ma5": 1.2448,
      "ma20": 1.316965,
      "prev_ma5": 1.29658,
      "prev_ma20": 1.32642,
      "macd_dif": -0.02684432,
      "macd_dea": -0.00372382,
      "macd_hist": -0.046241,
      "macd_trend": "bearish",
      "latest_price": 1.1143,
      "prices_used": 60
    },
    {
      "code": "014881",
      "name": "天弘中证机器人ETF联接C",
      "rsi14": 39.56,
      "ma5": 1.26088,
      "ma20": 1.31613,
      "prev_ma5": 1.26938,
      "prev_ma20": 1.321515,
      "macd_dif": -0.01869242,
      "macd_dea": -0.00671017,
      "macd_hist": -0.0239645,
      "macd_trend": "bearish",
      "latest_price": 1.2324,
      "prices_used": 60
    }
  ]
}