[
  {
    "code": "002963",
    "name": "易方达黄金ETF联接C",
    "price": 2.7983,
    "change_pct": -0.78,
    "updated_at": "2026-07-14"
  },
  {
    "code": "000307",
    "name": "易方达黄金ETF联接A",
    "price": 2.8871,
    "change_pct": -0.78,
    "updated_at": "2026-07-14"
  },
  {
    "code": "010990",
    "name": "南方有色金属ETF联接E",
    "price": 1.7309,
    "change_pct": 5.27,
    "updated_at": "2026-07-14"
  },
  {
    "code": "011840",
    "name": "天弘中证人工智能主题指数C",
    "price": 2.0823,
    "change_pct": 1.65,
    "updated_at": "2026-07-14"
  },
  {
    "code": "012885",
    "name": "华夏中证光伏产业ETF联接A",
    "price": 0.5465,
    "change_pct": 0.61,
    "updated_at": "2026-07-14"
  },
  {
    "code": "015790",
    "name": "永赢高端装备智选混合C",
    "price": 1.2712,
    "change_pct": -6.05,
    "updated_at": "2026-07-14"
  },
  {
    "code": "025647",
    "name": "平安高端装备混合C",
    "price": 1.1823,
    "change_pct": -4.35,
    "updated_at": "2026-07-15"
  },
  {
    "code": "014881",
    "name": "天弘中证机器人ETF联接C",
    "price": 1.238,
    "change_pct": 0.63,
    "updated_at": "2026-07-14"
  }
]