[
  {
    "code": "002963",
    "name": "易方达黄金ETF联接C",
    "price": 2.8197,
    "change_pct": 1.56,
    "updated_at": "2026-07-21"
  },
  {
    "code": "000307",
    "name": "易方达黄金ETF联接A",
    "price": 2.9094,
    "change_pct": 1.56,
    "updated_at": "2026-07-21"
  },
  {
    "code": "010990",
    "name": "南方有色金属ETF联接E",
    "price": 1.6718,
    "change_pct": 4.23,
    "updated_at": "2026-07-21"
  },
  {
    "code": "011840",
    "name": "天弘中证人工智能主题指数C",
    "price": 2.0057,
    "change_pct": 7.24,
    "updated_at": "2026-07-21"
  },
  {
    "code": "012885",
    "name": "华夏中证光伏产业ETF联接A",
    "price": 0.5225,
    "change_pct": 3.61,
    "updated_at": "2026-07-21"
  },
  {
    "code": "015790",
    "name": "永赢高端装备智选混合C",
    "price": 1.0682,
    "change_pct": 5.21,
    "updated_at": "2026-07-21"
  },
  {
    "code": "025647",
    "name": "平安高端装备混合C",
    "price": 1.005,
    "change_pct": 6.7,
    "updated_at": "2026-07-21"
  },
  {
    "code": "014881",
    "name": "天弘中证机器人ETF联接C",
    "price": 1.155,
    "change_pct": 4.13,
    "updated_at": "2026-07-21"
  }
]